{
  "id": "skill-github",
  "name": "GitHub API",
  "description": "Query GitHub repos, issues, and PRs via REST API",
  "triggerPatterns": ["github ", "repo info", "check issue", "github pr", "github repo"],
  "code": "const axios = require('axios');\nconst token = params.token || process.env.GITHUB_TOKEN || '';\nconst owner = params.owner;\nconst repo = params.repo;\nconst action = params.action || 'repo';\nconst headers = token ? { Authorization: `token ${token}` } : {};\nif (action === 'repo') {\n  const resp = await axios.get(`https://api.github.com/repos/${owner}/${repo}`, { headers });\n  return { name: resp.data.name, stars: resp.data.stargazers_count, forks: resp.data.forks_count, open_issues: resp.data.open_issues_count, description: resp.data.description };\n} else if (action === 'issues') {\n  const resp = await axios.get(`https://api.github.com/repos/${owner}/${repo}/issues?state=open&per_page=10`, { headers });\n  return { issues: resp.data.map(i => ({ number: i.number, title: i.title, state: i.state, url: i.html_url })) };\n} else if (action === 'prs') {\n  const resp = await axios.get(`https://api.github.com/repos/${owner}/${repo}/pulls?state=open&per_page=10`, { headers });\n  return { prs: resp.data.map(p => ({ number: p.number, title: p.title, author: p.user.login, url: p.html_url })) };\n} else {\n  throw new Error('Unknown action: ' + action);\n}",
  "language": "javascript",
  "tags": ["dev", "github", "api"],
  "version": 1
}
